[
 {
  "table":"/IWBEP/I_SBD_MD",
  "data":
  [
   {
    "PROJECT":"ZRO_DEMO_SEGW4",
    "NODE_UUID":"w4Do31aAHu6B1BRxxS+mjQ==",
    "NODE_UUID_PA":"w4Do31aAHu6B1BRxxS+GjQ==",
    "PLUGIN_PA":"/IWBEP/CORE",
    "NODE_TYPE_PA":"PROJ",
    "TECHNICAL_NAME":"",
    "VERSION":0,
    "MPC":"",
    "STATE_NS":"",
    "VALUE_NS":""
   }
  ]
 },
 {
  "table":"/IWBEP/I_SBD_MDT",
  "data":
  [
   {
    "SYLANGU":"E",
    "PROJECT":"ZRO_DEMO_SEGW4",
    "NODE_UUID":"w4Do31aAHu6B1BRxxS+mjQ==",
    "DESCRIPTION":""
   }
  ]
 },
 {
  "table":"/IWBEP/I_SBD_NOI",
  "data":
  [
   {
    "PROJECT":"ZRO_DEMO_SEGW4",
    "NODE_UUID":"w4Do31aAHu6B1BRxxS+GjQ==",
    "TYPE":"",
    "NAME":""
   },
   {
    "PROJECT":"ZRO_DEMO_SEGW4",
    "NODE_UUID":"w4Do31aAHu6B1BRxxS+mjQ==",
    "TYPE":"",
    "NAME":""
   },
   {
    "PROJECT":"ZRO_DEMO_SEGW4",
    "NODE_UUID":"w4Do31aAHu6B1BRxxS/GjQ==",
    "TYPE":"",
    "NAME":""
   }
  ]
 },
 {
  "table":"/IWBEP/I_SBD_PR",
  "data":
  [
   {
    "PROJECT":"ZRO_DEMO_SEGW4",
    "NODE_UUID":"w4Do31aAHu6B1BRxxS+GjQ==",
    "CREATION_USER_ID":"RAHUL",
    "CREATION_TIME":"+20230609083550.3609610",
    "LAST_CHG_USER_ID":"RAHUL",
    "LAST_CHG_TIME":"+20230609083550.3609650",
    "LAST_CHG_STATE":"w4Do31aAHu6B1B9NN/hm6g==",
    "PLUGIN":"/IWBEP/GEN",
    "STRAT_NAME":"0002",
    "STRAT_VERSION":"",
    "PROJECT_TYPE":"4"
   }
  ]
 },
 {
  "table":"/IWBEP/I_SBD_PRT",
  "data":
  [
   {
    "PROJECT":"ZRO_DEMO_SEGW4",
    "SYLANGU":"E",
    "DESCRIPTION":"zro_demo_segw4"
   }
  ]
 },
 {
  "table":"/IWBEP/I_SBD_SV",
  "data":
  [
   {
    "PROJECT":"ZRO_DEMO_SEGW4",
    "NODE_UUID":"w4Do31aAHu6B1BRxxS/GjQ==",
    "TECHNICAL_NAME":"",
    "VERSION":0,
    "DPC":"",
    "EXTERNAL_NAME":"",
    "MODEL":""
   }
  ]
 },
 {
  "table":"/IWBEP/I_SBD_SVT",
  "data":
  [
   {
    "SYLANGU":"E",
    "PROJECT":"ZRO_DEMO_SEGW4",
    "NODE_UUID":"w4Do31aAHu6B1BRxxS/GjQ==",
    "DESCRIPTION":""
   }
  ]
 },
 {
  "table":"TADIR",
  "data":
  [
   {
    "PGMID":"R3TR",
    "OBJECT":"IWPR",
    "OBJ_NAME":"ZRO_DEMO_SEGW4",
    "KORRNUM":"",
    "SRCSYSTEM":"...",
    "AUTHOR":"RAHUL",
    "SRCDEP":"",
    "DEVCLASS":"ZRO_DEMO",
    "GENFLAG":"",
    "EDTFLAG":"",
    "CPROJECT":" S",
    "MASTERLANG":"E",
    "VERSID":"",
    "PAKNOCHECK":"",
    "OBJSTABLTY":"",
    "COMPONENT":"",
    "CRELEASE":"",
    "DELFLAG":"",
    "TRANSLTTXT":"",
    "CREATED_ON":"2023-06-09",
    "CHECK_DATE":"2023-06-09",
    "CHECK_CFG":""
   }
  ]
 }
]